characteristic-stubs/METADATA.toml
characteristic-stubs/__init__.pyi
types_characteristic-14.3.6.dist-info/METADATA
types_characteristic-14.3.6.dist-info/WHEEL
types_characteristic-14.3.6.dist-info/top_level.txt
types_characteristic-14.3.6.dist-info/RECORD
